MANIFEST.in
README.rst
setup.py
dudebot/__init__.py
dudebot/__main__.py
dudebot/classutil.py
dudebot/core.py
dudebot/debug.py
dudebot/decorators.py
dudebot/jabber.py
dudebot/oldmain.py
dudebot.egg-info/PKG-INFO
dudebot.egg-info/SOURCES.txt
dudebot.egg-info/dependency_links.txt
dudebot.egg-info/requires.txt
dudebot.egg-info/top_level.txt
dudebot/examples/__init__.py
dudebot/examples/demo.py
dudebot/examples/google.py
dudebot/examples/sedbot.py