Metadata-Version: 1.0
Name: dudebot
Version: 0.0.8
Summary: A really simple framework for chatroom bots
Home-page: https://github.com/sujaymansingh/dudebot
Author: Sujay Mansingh
Author-email: sujay.mansingh@gmail.com
License: LICENSE.txt
Platform: UNKNOWN
